pydantic_ai/__init__.py
pydantic_ai/_griffe.py
pydantic_ai/_pydantic.py
pydantic_ai/_result.py
pydantic_ai/_system_prompt.py
pydantic_ai/_utils.py
pydantic_ai/agent.py
pydantic_ai/exceptions.py
pydantic_ai/messages.py
pydantic_ai/models/__init__.py
pydantic_ai/models/function.py
pydantic_ai/models/gemini.py
pydantic_ai/models/groq.py
pydantic_ai/models/ollama.py
pydantic_ai/models/openai.py
pydantic_ai/models/test.py
pydantic_ai/models/vertexai.py
pydantic_ai/py.typed
pydantic_ai/result.py
pydantic_ai/tools.py
ftech_pydantic_ai-0.0.12.dist-info/LICENSE
ftech_pydantic_ai-0.0.12.dist-info/METADATA
ftech_pydantic_ai-0.0.12.dist-info/WHEEL
ftech_pydantic_ai-0.0.12.dist-info/RECORD
