Metadata-Version: 2.1
Name: ftech-pydantic-ai
Version: 0.0.12
Summary: Agent Framework / shim to use Pydantic with LLMs, slim package
License: MIT
Author: Samuel Colvin
Author-email: samuel@pydantic.dev
Requires-Python: >=3.9
Classifier: Development Status :: 4 - Beta
Classifier: Environment :: Console
Classifier: Environment :: MacOS X
Classifier: Intended Audience :: Developers
Classifier: Intended Audience :: Information Technology
Classifier: Intended Audience :: System Administrators
Classifier: License :: OSI Approved :: MIT License
Classifier: Operating System :: POSIX :: Linux
Classifier: Operating System :: Unix
Classifier: Programming Language :: Python
Classifier: Programming Language :: Python :: 3
Classifier: Programming Language :: Python :: 3.9
Classifier: Programming Language :: Python :: 3.10
Classifier: Programming Language :: Python :: 3.11
Classifier: Programming Language :: Python :: 3.12
Classifier: Programming Language :: Python :: 3 :: Only
Classifier: Programming Language :: Python :: 3.13
Classifier: Topic :: Internet
Classifier: Topic :: Software Development :: Libraries :: Python Modules
Provides-Extra: groq
Provides-Extra: logfire
Provides-Extra: openai
Provides-Extra: vertexai
Requires-Dist: eval-type-backport (>=0.2.0)
Requires-Dist: griffe (>=1.3.2)
Requires-Dist: httpx (>=0.27.2)
Requires-Dist: logfire-api (>=1.2.0)
Requires-Dist: pydantic (>=2.10)
